nonebot_plugin_llnonebot_api-0.1.0.dist-info/METADATA
nonebot_plugin_llnonebot_api-0.1.0.dist-info/WHEEL
nonebot_plugin_llnonebot_api-0.1.0.dist-info/entry_points.txt
nonebot_plugin_llnonebot_api-0.1.0.dist-info/licenses/LICENSE
nonebot_plugin_llnonebot_api/__init__.py
nonebot_plugin_llnonebot_api/about/router.py
nonebot_plugin_llnonebot_api/about/schema.py
nonebot_plugin_llnonebot_api/log/router.py
nonebot_plugin_llnonebot_api/logging.py
nonebot_plugin_llnonebot_api/router.py
nonebot_plugin_llnonebot_api-0.1.0.dist-info/RECORD
