Metadata-Version: 2.1
Name: nonebot-plugin-llnonebot-api
Version: 0.1.0
Summary: 为 LLNoneBot 提供 API 服务 / Provide API services for LLNoneBot
Author-Email: KomoriDev <mute231010@gmail.com>
License: MIT
Requires-Python: >=3.9
Requires-Dist: nonebot2>=2.3.3
Requires-Dist: fastapi>=0.115.0
